rdmo/__init__.py
rdmo/__main__.py
rdmo/accounts/__init__.py
rdmo/accounts/account.py
rdmo/accounts/admin.py
rdmo/accounts/apps.py
rdmo/accounts/checks.py
rdmo/accounts/forms.py
rdmo/accounts/middleware.py
rdmo/accounts/models.py
rdmo/accounts/settings.py
rdmo/accounts/socialaccount.py
rdmo/accounts/utils.py
rdmo/accounts/views.py
rdmo/accounts/viewsets.py
rdmo/accounts/migrations/0001_initial.py
rdmo/accounts/migrations/0002_detail_key_type_field_length_increased.py
rdmo/accounts/migrations/0003_hint_renamed_to_help_text.py
rdmo/accounts/migrations/0004_permission_added.py
rdmo/accounts/migrations/0005_field_type.py
rdmo/accounts/migrations/0006_permissions_removed.py
rdmo/accounts/migrations/0007_additional_fields.py
rdmo/accounts/migrations/0008_related_name.py
rdmo/accounts/migrations/0009_proxyuser.py
rdmo/accounts/migrations/0010_consentfieldvalue.py
rdmo/accounts/migrations/0011_rename_en_to_lang1.py
rdmo/accounts/migrations/0012_rename_de_to_lang2.py
rdmo/accounts/migrations/0013_meta.py
rdmo/accounts/migrations/0014_add_language_fields.py
rdmo/accounts/migrations/0015_data_migration.py
rdmo/accounts/migrations/0016_remove_null_true.py
rdmo/accounts/migrations/0017_role.py
rdmo/accounts/migrations/0018_blank_fields.py
rdmo/accounts/migrations/0019_delete_proxyuser.py
rdmo/accounts/migrations/0020_add_role_editor_and_reviewer.py
rdmo/accounts/migrations/0021_alter_help_text.py
rdmo/accounts/migrations/0022_add_created_updated_to_consent.py
rdmo/accounts/migrations/__init__.py
rdmo/accounts/serializers/__init__.py
rdmo/accounts/serializers/v1.py
rdmo/accounts/static/accounts/img/keycloak_logo_200px.svg
rdmo/accounts/static/accounts/img/orcid-signin.png
rdmo/accounts/static/accounts/img/orcid_16x16.png
rdmo/accounts/templates/account/account_token.html
rdmo/accounts/templates/account/email.html
rdmo/accounts/templates/account/email_confirm.html
rdmo/accounts/templates/account/login.html
rdmo/accounts/templates/account/login_form.html
rdmo-2.4.0.dist-info/licenses/AUTHORS
rdmo-2.4.0.dist-info/licenses/LICENSE
rdmo-2.4.0.dist-info/licenses/NOTICE
rdmo-2.4.0.dist-info/METADATA
rdmo-2.4.0.dist-info/WHEEL
rdmo-2.4.0.dist-info/entry_points.txt
rdmo-2.4.0.dist-info/top_level.txt
rdmo-2.4.0.dist-info/RECORD
