Metadata-Version: 2.4
Name: rdmo
Version: 2.4.0
Summary: RDMO is a tool to support the systematic planning, organisation and implementation of the data management throughout the course of a research project.
Author-email: RDMO Arbeitsgemeinschaft <rdmo-team@listserv.dfn.de>
License-Expression: Apache-2.0
Project-URL: changelog, https://github.com/rdmorganiser/rdmo/blob/main/CHANGELOG.md
Project-URL: documentation, https://rdmo.readthedocs.io
Project-URL: homepage, https://rdmorganiser.github.io
Project-URL: issues, https://github.com/rdmorganiser/rdmo/issues
Project-URL: repository, https://github.com/rdmorganiser/rdmo.git
Project-URL: slack, https://rdmo.slack.com
Keywords: data management plan,dmp,rdmo,research data,research data management
Classifier: Development Status :: 5 - Production/Stable
Classifier: Environment :: Web Environment
Classifier: Framework :: Django :: 4.2
Classifier: Intended Audience :: Science/Research
Classifier: Operating System :: OS Independent
Classifier: Programming Language :: Python
Classifier: Programming Language :: Python :: 3 :: Only
Classifier: Programming Language :: Python :: 3.10
Classifier: Programming Language :: Python :: 3.11
Classifier: Programming Language :: Python :: 3.12
Classifier: Programming Language :: Python :: 3.13
Requires-Python: >=3.10
License-File: LICENSE
License-File: NOTICE
License-File: AUTHORS
Requires-Dist: defusedcsv<4.0,>=2.0
Requires-Dist: defusedxml<1.0,>=0.7.1
Requires-Dist: django<5.0,>=4.2
Requires-Dist: django-cleanup<10.0,>=8.0
Requires-Dist: django-compressor<5.0,>=4.4
Requires-Dist: django-extensions<5.0,>=3.2
Requires-Dist: django-filter<26.0,>=23.2
Requires-Dist: django-libsass<1.0,>=0.9
Requires-Dist: django-mathfilters<2.0,>=1.0
Requires-Dist: django-mptt<1.0.0,>=0.16.0
Requires-Dist: django-settings-export<2.0,>=1.2
Requires-Dist: django-split-settings<2.0,>=1.2
Requires-Dist: django-widget-tweaks<2.0,>=1.5
Requires-Dist: djangorestframework<4.0,>=3.15
Requires-Dist: drf-extensions<1.0,>=0.7.1
Requires-Dist: iso8601<3.0,>=2.0
Requires-Dist: markdown<4.0,>=3.4
Requires-Dist: packaging<26.0,>=23.2
Requires-Dist: pypandoc<2.0,>=1.11
Requires-Dist: requests-toolbelt<2.0,>=1.0
Requires-Dist: rules<4.0,>=3.4
Provides-Extra: all
Requires-Dist: rdmo[allauth,dev,gunicorn,ldap,mysql,openapi,postgres,pytest]; extra == "all"
Provides-Extra: recommended
Requires-Dist: rdmo[allauth,gunicorn,openapi,postgres]; extra == "recommended"
Provides-Extra: ci
Requires-Dist: rdmo[allauth,dev,openapi,pytest]; extra == "ci"
Requires-Dist: pytest-github-actions-annotate-failures<0.4.0,>=0.2.0; extra == "ci"
Provides-Extra: allauth
Requires-Dist: django-allauth[openid,socialaccount]<65.14.0,>=64.1.0; extra == "allauth"
Provides-Extra: dev
Requires-Dist: pipdeptree<3.0,>=2.13; extra == "dev"
Requires-Dist: pre-commit<5.0,>=3.4; extra == "dev"
Requires-Dist: setuptools<81,>=73; extra == "dev"
Provides-Extra: gunicorn
Requires-Dist: gunicorn<24.0,>=23.0; extra == "gunicorn"
Provides-Extra: ldap
Requires-Dist: django-auth-ldap<6.0,>=4.5; extra == "ldap"
Provides-Extra: mysql
Requires-Dist: mysqlclient<3.0,>=2.2; extra == "mysql"
Provides-Extra: openapi
Requires-Dist: drf-spectacular[sidecar]<1.0.0,>=0.28.0; extra == "openapi"
Provides-Extra: postgres
Requires-Dist: psycopg[binary]<4.0,>=3.1; extra == "postgres"
Provides-Extra: pytest
Requires-Dist: pytest<10.0,>=9.0; extra == "pytest"
Requires-Dist: pytest-cov<8.0,>=7.0; extra == "pytest"
Requires-Dist: pytest-django<5.0,>=4.11; extra == "pytest"
Requires-Dist: pytest-mock<4.0,>=3.15; extra == "pytest"
Requires-Dist: pytest-playwright<0.8.0,>=0.7.2; extra == "pytest"
Requires-Dist: pytest-randomly<5.0,>=4.0; extra == "pytest"
Requires-Dist: pytest-xdist<4.0,>=3.8; extra == "pytest"
Dynamic: license-file
